onellm/.version
onellm/__init__.py
onellm/audio.py
onellm/cache.py
onellm/chat_completion.py
onellm/client.py
onellm/completion.py
onellm/config.py
onellm/embedding.py
onellm/errors.py
onellm/files.py
onellm/http_pool.py
onellm/image.py
onellm/models.py
onellm/speech.py
onellm/validators.py
onellm/cli/__init__.py
onellm/cli/download_model.py
onellm/providers/__init__.py
onellm/providers/anthropic.py
onellm/providers/anthropic_compatible.py
onellm/providers/anyscale.py
onellm/providers/azure.py
onellm/providers/base.py
onellm/providers/bedrock.py
onellm/providers/cohere.py
onellm/providers/deepseek.py
onellm/providers/fallback.py
onellm/providers/fireworks.py
onellm/providers/glm.py
onellm/providers/google.py
onellm/providers/groq.py
onellm/providers/llama_cpp.py
onellm/providers/minimax.py
onellm/providers/mistral.py
onellm/providers/moonshot.py
onellm/providers/ollama.py
onellm/providers/openai.py
onellm/providers/openai_compatible.py
onellm/providers/openrouter.py
onellm/providers/perplexity.py
onellm/providers/together.py
onellm/providers/vercel.py
onellm/providers/vertexai.py
onellm/providers/xai.py
onellm/types/__init__.py
onellm/types/common.py
onellm/utils/__init__.py
onellm/utils/async_helpers.py
onellm/utils/fallback.py
onellm/utils/file_validator.py
onellm/utils/retry.py
onellm/utils/streaming.py
onellm/utils/text_cleaner.py
onellm/utils/token_counter.py
onellm-0.20260130.0.dist-info/licenses/LICENSE
onellm-0.20260130.0.dist-info/METADATA
onellm-0.20260130.0.dist-info/WHEEL
onellm-0.20260130.0.dist-info/entry_points.txt
onellm-0.20260130.0.dist-info/top_level.txt
onellm-0.20260130.0.dist-info/RECORD
