Metadata-Version: 2.4
Name: onellm
Version: 0.20260130.0
Summary: A unified interface for interacting with large language models from various providers - a complete drop-in replacement for OpenAI's client
Author-email: Ran Aroussi <ran@aroussi.com>
License: Apache-2.0
Project-URL: Homepage, https://github.com/muxi-ai/onellm
Project-URL: Documentation, https://docs.muxi.io
Project-URL: Issues, https://github.com/muxi-ai/onellm/issues
Classifier: Development Status :: 5 - Production/Stable
Classifier: Intended Audience :: Developers
Classifier: License :: OSI Approved :: Apache Software License
Classifier: Programming Language :: Python :: 3
Classifier: Programming Language :: Python :: 3.10
Classifier: Programming Language :: Python :: 3.11
Classifier: Topic :: Software Development :: Libraries :: Python Modules
Requires-Python: >=3.10
License-File: LICENSE
Requires-Dist: requests>=2.32.5
Requires-Dist: aiohttp>=3.13.3
Requires-Dist: pydantic>=2.12.5
Requires-Dist: PyYAML>=6.0.3
Requires-Dist: openai>=2.15.0
Requires-Dist: tiktoken>=0.12.0
Requires-Dist: huggingface-hub>=1.3.4
Requires-Dist: urllib3>=2.6.3
Requires-Dist: filelock>=3.20.3
Requires-Dist: pyasn1>=0.6.2
Provides-Extra: cache
Requires-Dist: sentence-transformers>=5.2.2; extra == "cache"
Requires-Dist: faiss-cpu>=1.13.2; extra == "cache"
Provides-Extra: all
Requires-Dist: anthropic>=0.76.0; extra == "all"
Requires-Dist: google-generativeai>=0.8.6; extra == "all"
Requires-Dist: boto3>=1.42.35; extra == "all"
Requires-Dist: llama-cpp-python>=0.3.16; extra == "all"
Requires-Dist: google-auth>=2.48.0; extra == "all"
Requires-Dist: google-cloud-aiplatform>=1.134.0; extra == "all"
Requires-Dist: sentence-transformers>=5.2.2; extra == "all"
Requires-Dist: faiss-cpu>=1.13.2; extra == "all"
Provides-Extra: bedrock
Requires-Dist: boto3>=1.42.35; extra == "bedrock"
Provides-Extra: vertexai
Requires-Dist: google-auth>=2.48.0; extra == "vertexai"
Requires-Dist: google-cloud-aiplatform>=1.134.0; extra == "vertexai"
Provides-Extra: llama
Requires-Dist: llama-cpp-python>=0.3.16; extra == "llama"
Provides-Extra: dev
Requires-Dist: pytest>=9.0.2; extra == "dev"
Requires-Dist: pytest-asyncio>=1.3.0; extra == "dev"
Requires-Dist: pytest-cov>=7.0.0; extra == "dev"
Requires-Dist: black>=26.1.0; extra == "dev"
Requires-Dist: isort>=7.0.0; extra == "dev"
Requires-Dist: mypy>=1.19.1; extra == "dev"
Requires-Dist: ruff>=0.14.14; extra == "dev"
Requires-Dist: python-dotenv>=1.2.1; extra == "dev"
Dynamic: license-file
